wavesplit/__init__.py
wavesplit/_modidx.py
wavesplit/core.py
wavesplit-0.0.3.dist-info/LICENSE.txt
wavesplit-0.0.3.dist-info/METADATA
wavesplit-0.0.3.dist-info/WHEEL
wavesplit-0.0.3.dist-info/entry_points.txt
wavesplit-0.0.3.dist-info/top_level.txt
wavesplit-0.0.3.dist-info/RECORD
