Metadata-Version: 2.1
Name: wavesplit
Version: 0.0.3
Summary: A package for splitting waves and merging them
Home-page: https://github.com/SpeechifyInc/wavesplit
Author: tyler
Author-email: tylerweitzman@gmail.com
License: GNU General Public License v2
Keywords: nbdev jupyter notebook python
Platform: UNKNOWN
Classifier: Development Status :: 4 - Beta
Classifier: Intended Audience :: Developers
Classifier: Natural Language :: English
Classifier: Programming Language :: Python :: 3.7
Classifier: Programming Language :: Python :: 3.8
Classifier: Programming Language :: Python :: 3.9
Classifier: Programming Language :: Python :: 3.10
Classifier: License :: OSI Approved :: GNU General Public License v2 (GPLv2)
Requires-Python: >=3.7
License-File: LICENSE.txt
Provides-Extra: dev
